workshop2/__init__.py
workshop2/add.py
workshop2-0.1.0.dist-info/METADATA
workshop2-0.1.0.dist-info/WHEEL
workshop2-0.1.0.dist-info/entry_points.txt
workshop2-0.1.0.dist-info/RECORD
