Metadata-Version: 2.4
Name: workshop2
Version: 0.1.0
Summary: Add your description here
Requires-Python: >=3.12
Requires-Dist: pytest>=8.3.5
Requires-Dist: ruff>=0.11.2
